README.rst
setup.cfg
setup.py
s3_image_optimizer/__init__.py
s3_image_optimizer/cli.py
s3_image_optimizer.egg-info/PKG-INFO
s3_image_optimizer.egg-info/SOURCES.txt
s3_image_optimizer.egg-info/dependency_links.txt
s3_image_optimizer.egg-info/entry_points.txt
s3_image_optimizer.egg-info/not-zip-safe
s3_image_optimizer.egg-info/requires.txt
s3_image_optimizer.egg-info/top_level.txt