Metadata-Version: 1.1
Name: s3-image-optimizer
Version: 0.1.0
Summary: S3 Image Optimizer optimizes all images found in an Amazon S3 bucket.
Home-page: https://github.com/svengt/s3-image-optimizer
Author: Sven Groot
Author-email: sven@mediamoose.nl
License: BSD
Download-URL: https://github.com/svengt/s3-image-optimizer/tarball/0.1.0
Keywords: s3,image,optimization,amazon,aws,boto
Platform: any
Classifier: Development Status :: 4 - Beta
Classifier: Environment :: Console
Classifier: Intended Audience :: Developers
Classifier: License :: OSI Approved :: BSD License
Classifier: Operating System :: POSIX
Classifier: Operating System :: MacOS
Classifier: Operating System :: Unix
Classifier: Programming Language :: Python
Classifier: Programming Language :: Python :: 2
Classifier: Programming Language :: Python :: 3
Classifier: Topic :: Software Development :: Libraries :: Python Modules
